odoo/addons/shopinvader_search_engine_product_seo/README.rst
odoo/addons/shopinvader_search_engine_product_seo/__init__.py
odoo/addons/shopinvader_search_engine_product_seo/__manifest__.py
odoo/addons/shopinvader_search_engine_product_seo/i18n/shopinvader_search_engine_product_seo.pot
odoo/addons/shopinvader_search_engine_product_seo/models/__init__.py
odoo/addons/shopinvader_search_engine_product_seo/models/product_template.py
odoo/addons/shopinvader_search_engine_product_seo/models/se_backend.py
odoo/addons/shopinvader_search_engine_product_seo/readme/CONFIGURATION.rst
odoo/addons/shopinvader_search_engine_product_seo/readme/CONTRIBUTORS.rst
odoo/addons/shopinvader_search_engine_product_seo/readme/DESCRIPTION.rst
odoo/addons/shopinvader_search_engine_product_seo/static/description/index.html
odoo/addons/shopinvader_search_engine_product_seo/tests/__init__.py
odoo/addons/shopinvader_search_engine_product_seo/tests/test_product_seo_title.py
odoo/addons/shopinvader_search_engine_product_seo/views/se_backend.xml
odoo_addon_shopinvader_search_engine_product_seo-16.0.1.0.1.dist-info/METADATA
odoo_addon_shopinvader_search_engine_product_seo-16.0.1.0.1.dist-info/WHEEL
odoo_addon_shopinvader_search_engine_product_seo-16.0.1.0.1.dist-info/top_level.txt
odoo_addon_shopinvader_search_engine_product_seo-16.0.1.0.1.dist-info/RECORD
